pronounceable/__init__.py
pronounceable/complexity.py
pronounceable/components.py
pronounceable/digraph.py
pronounceable/dir.py
pronounceable/main.py
pronounceable/database/google-10000-english.txt
pronounceable/database/leetspeak.yaml
pronounceable-0.1.3.dist-info/METADATA
pronounceable-0.1.3.dist-info/RECORD
pronounceable-0.1.3.dist-info/WHEEL
pronounceable-0.1.3.dist-info/top_level.txt
