Metadata-Version: 2.1
Name: pronounceable
Version: 0.1.3
Summary: Analyze passwords' memorizability and generate pronounceable words.
Home-page: https://github.com/patarapolw/pronounceable
Author: Pacharapol Withayasakpunt
Author-email: patarapolw@gmail.com
License: MIT
Keywords: password password-analysis nltk word-synthesis
Platform: UNKNOWN
Classifier: Development Status :: 4 - Beta
Classifier: Environment :: Console
Classifier: Intended Audience :: Developers
Classifier: Intended Audience :: Information Technology
Classifier: Intended Audience :: System Administrators
Classifier: License :: OSI Approved :: MIT License
Classifier: Natural Language :: English
Classifier: Programming Language :: Python :: 3.5
Classifier: Programming Language :: Python :: 3.6
Classifier: Topic :: Security :: Cryptography
Requires-Python: >=3.5
Provides-Extra: analysis
Provides-Extra: tests
Requires-Dist: nltk
Requires-Dist: PyYAML
Requires-Dist: metaphone
Provides-Extra: analysis
Requires-Dist: memorable-password; extra == 'analysis'
Requires-Dist: randomsentence; extra == 'analysis'
Provides-Extra: tests
Requires-Dist: pytest; extra == 'tests'
Requires-Dist: pytest-doctestplus; extra == 'tests'
